{
  "updatedAt": "2026-06-20T09:09:10+00:00",
  "source": "the-odds-api",
  "sourcesTried": [
    {
      "source": "the-odds-api",
      "ok": true,
      "count": 40
    },
    {
      "source": "espn",
      "ok": false,
      "error": "'NoneType' object has no attribute 'get'"
    }
  ],
  "count": 40,
  "odds": [
    {
      "date": "2026-06-20",
      "home": "Germany",
      "away": "Côte d'Ivoire",
      "home_odds": 1.5592,
      "draw_odds": 4.5243,
      "away_odds": 6.0182,
      "p_home": 0.6236,
      "p_draw": 0.2149,
      "p_away": 0.1616,
      "bookmaker": "avg(49)",
      "source": "the-odds-api"
    },
    {
      "date": "2026-06-20",
      "home": "Netherlands",
      "away": "Sweden",
      "home_odds": 1.7758,
      "draw_odds": 3.9537,
      "away_odds": 4.7681,
      "p_home": 0.549,
      "p_draw": 0.2466,
      "p_away": 0.2045,
      "bookmaker": "avg(48)",
      "source": "the-odds-api"
    },
    {
      "date": "2026-06-21",
      "home": "Belgium",
      "away": "Iran",
      "home_odds": 1.4229,
      "draw_odds": 4.6067,
      "away_odds": 7.6157,
      "p_home": 0.6686,
      "p_draw": 0.2065,
      "p_away": 0.1249,
      "bookmaker": "avg(49)",
      "source": "the-odds-api"
    },
    {
      "date": "2026-06-21",
      "home": "Ecuador",
      "away": "Curaçao",
      "home_odds": 1.171,
      "draw_odds": 9.119,
      "away_odds": 22.0488,
      "p_home": 0.8464,
      "p_draw": 0.1087,
      "p_away": 0.045,
      "bookmaker": "avg(49)",
      "source": "the-odds-api"
    },
    {
      "date": "2026-06-21",
      "home": "Spain",
      "away": "Saudi Arabia",
      "home_odds": 1.0918,
      "draw_odds": 10.6906,
      "away_odds": 27.5878,
      "p_home": 0.8759,
      "p_draw": 0.0895,
      "p_away": 0.0347,
      "bookmaker": "avg(49)",
      "source": "the-odds-api"
    },
    {
      "date": "2026-06-21",
      "home": "Tunisia",
      "away": "Japan",
      "home_odds": 6.3639,
      "draw_odds": 3.8957,
      "away_odds": 1.6292,
      "p_home": 0.1529,
      "p_draw": 0.2498,
      "p_away": 0.5973,
      "bookmaker": "avg(49)",
      "source": "the-odds-api"
    },
    {
      "date": "2026-06-21",
      "home": "Uruguay",
      "away": "Cape Verde Islands",
      "home_odds": 1.439,
      "draw_odds": 4.2257,
      "away_odds": 8.2627,
      "p_home": 0.6602,
      "p_draw": 0.2248,
      "p_away": 0.115,
      "bookmaker": "avg(49)",
      "source": "the-odds-api"
    },
    {
      "date": "2026-06-22",
      "home": "Argentina",
      "away": "Austria",
      "home_odds": 1.5739,
      "draw_odds": 3.9341,
      "away_odds": 6.1143,
      "p_home": 0.6033,
      "p_draw": 0.2414,
      "p_away": 0.1553,
      "bookmaker": "avg(49)",
      "source": "the-odds-api"
    },
    {
      "date": "2026-06-22",
      "home": "France",
      "away": "Iraq",
      "home_odds": 1.0877,
      "draw_odds": 11.0694,
      "away_odds": 29.5552,
      "p_home": 0.881,
      "p_draw": 0.0866,
      "p_away": 0.0324,
      "bookmaker": "avg(48)",
      "source": "the-odds-api"
    },
    {
      "date": "2026-06-22",
      "home": "New Zealand",
      "away": "Egypt",
      "home_odds": 5.6388,
      "draw_odds": 4.0657,
      "away_odds": 1.5959,
      "p_home": 0.1689,
      "p_draw": 0.2343,
      "p_away": 0.5968,
      "bookmaker": "avg(49)",
      "source": "the-odds-api"
    },
    {
      "date": "2026-06-23",
      "home": "England",
      "away": "Ghana",
      "home_odds": 1.2152,
      "draw_odds": 6.5058,
      "away_odds": 14.1092,
      "p_home": 0.7856,
      "p_draw": 0.1467,
      "p_away": 0.0677,
      "bookmaker": "avg(48)",
      "source": "the-odds-api"
    },
    {
      "date": "2026-06-23",
      "home": "Jordan",
      "away": "Algeria",
      "home_odds": 5.8838,
      "draw_odds": 4.1058,
      "away_odds": 1.5719,
      "p_home": 0.1619,
      "p_draw": 0.232,
      "p_away": 0.6061,
      "bookmaker": "avg(48)",
      "source": "the-odds-api"
    },
    {
      "date": "2026-06-23",
      "home": "Norway",
      "away": "Senegal",
      "home_odds": 2.2879,
      "draw_odds": 3.4546,
      "away_odds": 3.089,
      "p_home": 0.4162,
      "p_draw": 0.2756,
      "p_away": 0.3082,
      "bookmaker": "avg(48)",
      "source": "the-odds-api"
    },
    {
      "date": "2026-06-23",
      "home": "Panama",
      "away": "Croatia",
      "home_odds": 6.6898,
      "draw_odds": 3.9869,
      "away_odds": 1.536,
      "p_home": 0.1422,
      "p_draw": 0.2386,
      "p_away": 0.6192,
      "bookmaker": "avg(48)",
      "source": "the-odds-api"
    },
    {
      "date": "2026-06-23",
      "home": "Portugal",
      "away": "Uzbekistan",
      "home_odds": 1.201,
      "draw_odds": 6.8019,
      "away_odds": 14.8319,
      "p_home": 0.7952,
      "p_draw": 0.1404,
      "p_away": 0.0644,
      "bookmaker": "avg(48)",
      "source": "the-odds-api"
    },
    {
      "date": "2026-06-24",
      "home": "Bosnia & Herzegovina",
      "away": "Qatar",
      "home_odds": 1.4317,
      "draw_odds": 4.7885,
      "away_odds": 6.8647,
      "p_home": 0.6633,
      "p_draw": 0.1983,
      "p_away": 0.1383,
      "bookmaker": "avg(47)",
      "source": "the-odds-api"
    },
    {
      "date": "2026-06-24",
      "home": "Colombia",
      "away": "Congo DR",
      "home_odds": 1.4946,
      "draw_odds": 4.1596,
      "away_odds": 7.0865,
      "p_home": 0.6369,
      "p_draw": 0.2288,
      "p_away": 0.1343,
      "bookmaker": "avg(46)",
      "source": "the-odds-api"
    },
    {
      "date": "2026-06-24",
      "home": "Morocco",
      "away": "Haiti",
      "home_odds": 1.1987,
      "draw_odds": 6.6683,
      "away_odds": 14.8259,
      "p_home": 0.7933,
      "p_draw": 0.1426,
      "p_away": 0.0641,
      "bookmaker": "avg(46)",
      "source": "the-odds-api"
    },
    {
      "date": "2026-06-24",
      "home": "Scotland",
      "away": "Brazil",
      "home_odds": 7.7335,
      "draw_odds": 5.0433,
      "away_odds": 1.3776,
      "p_home": 0.1227,
      "p_draw": 0.1882,
      "p_away": 0.689,
      "bookmaker": "avg(46)",
      "source": "the-odds-api"
    },
    {
      "date": "2026-06-24",
      "home": "Switzerland",
      "away": "Canada",
      "home_odds": 2.4296,
      "draw_odds": 3.0585,
      "away_odds": 3.1734,
      "p_home": 0.3906,
      "p_draw": 0.3103,
      "p_away": 0.2991,
      "bookmaker": "avg(47)",
      "source": "the-odds-api"
    },
    {
      "date": "2026-06-25",
      "home": "Curaçao",
      "away": "Côte d'Ivoire",
      "home_odds": 19.4409,
      "draw_odds": 8.7705,
      "away_odds": 1.1277,
      "p_home": 0.0489,
      "p_draw": 0.1084,
      "p_away": 0.8428,
      "bookmaker": "avg(43)",
      "source": "the-odds-api"
    },
    {
      "date": "2026-06-25",
      "home": "Czechia",
      "away": "Mexico",
      "home_odds": 3.5151,
      "draw_odds": 3.677,
      "away_odds": 2.0051,
      "p_home": 0.2696,
      "p_draw": 0.2577,
      "p_away": 0.4726,
      "bookmaker": "avg(43)",
      "source": "the-odds-api"
    },
    {
      "date": "2026-06-25",
      "home": "Ecuador",
      "away": "Germany",
      "home_odds": 4.9405,
      "draw_odds": 3.8205,
      "away_odds": 1.6863,
      "p_home": 0.1915,
      "p_draw": 0.2476,
      "p_away": 0.5609,
      "bookmaker": "avg(43)",
      "source": "the-odds-api"
    },
    {
      "date": "2026-06-25",
      "home": "Japan",
      "away": "Sweden",
      "home_odds": 2.1656,
      "draw_odds": 3.39,
      "away_odds": 3.3184,
      "p_home": 0.4364,
      "p_draw": 0.2788,
      "p_away": 0.2848,
      "bookmaker": "avg(43)",
      "source": "the-odds-api"
    },
    {
      "date": "2026-06-25",
      "home": "South Africa",
      "away": "South Korea",
      "home_odds": 5.7482,
      "draw_odds": 3.9059,
      "away_odds": 1.6043,
      "p_home": 0.1652,
      "p_draw": 0.2431,
      "p_away": 0.5918,
      "bookmaker": "avg(44)",
      "source": "the-odds-api"
    },
    {
      "date": "2026-06-25",
      "home": "Tunisia",
      "away": "Netherlands",
      "home_odds": 9.7479,
      "draw_odds": 5.4081,
      "away_odds": 1.2995,
      "p_home": 0.0971,
      "p_draw": 0.1749,
      "p_away": 0.728,
      "bookmaker": "avg(43)",
      "source": "the-odds-api"
    },
    {
      "date": "2026-06-26",
      "home": "Norway",
      "away": "France",
      "home_odds": 4.2324,
      "draw_odds": 3.7438,
      "away_odds": 1.7945,
      "p_home": 0.2228,
      "p_draw": 0.2518,
      "p_away": 0.5254,
      "bookmaker": "avg(42)",
      "source": "the-odds-api"
    },
    {
      "date": "2026-06-26",
      "home": "Paraguay",
      "away": "Australia",
      "home_odds": 2.7221,
      "draw_odds": 2.3402,
      "away_odds": 3.7424,
      "p_home": 0.346,
      "p_draw": 0.4024,
      "p_away": 0.2516,
      "bookmaker": "avg(42)",
      "source": "the-odds-api"
    },
    {
      "date": "2026-06-26",
      "home": "Senegal",
      "away": "Iraq",
      "home_odds": 1.2919,
      "draw_odds": 5.336,
      "away_odds": 10.4736,
      "p_home": 0.7324,
      "p_draw": 0.1773,
      "p_away": 0.0903,
      "bookmaker": "avg(42)",
      "source": "the-odds-api"
    },
    {
      "date": "2026-06-26",
      "home": "Türkiye",
      "away": "United States",
      "home_odds": 3.051,
      "draw_odds": 3.8829,
      "away_odds": 2.115,
      "p_home": 0.3098,
      "p_draw": 0.2434,
      "p_away": 0.4468,
      "bookmaker": "avg(42)",
      "source": "the-odds-api"
    },
    {
      "date": "2026-06-27",
      "home": "Cape Verde Islands",
      "away": "Saudi Arabia",
      "home_odds": 2.7395,
      "draw_odds": 3.5748,
      "away_odds": 2.4055,
      "p_home": 0.3442,
      "p_draw": 0.2638,
      "p_away": 0.392,
      "bookmaker": "avg(42)",
      "source": "the-odds-api"
    },
    {
      "date": "2026-06-27",
      "home": "Colombia",
      "away": "Portugal",
      "home_odds": 3.5195,
      "draw_odds": 3.4212,
      "away_odds": 2.0576,
      "p_home": 0.2674,
      "p_draw": 0.2751,
      "p_away": 0.4575,
      "bookmaker": "avg(41)",
      "source": "the-odds-api"
    },
    {
      "date": "2026-06-27",
      "home": "Congo DR",
      "away": "Uzbekistan",
      "home_odds": 2.1044,
      "draw_odds": 3.5483,
      "away_odds": 3.2734,
      "p_home": 0.4472,
      "p_draw": 0.2652,
      "p_away": 0.2875,
      "bookmaker": "avg(41)",
      "source": "the-odds-api"
    },
    {
      "date": "2026-06-27",
      "home": "Croatia",
      "away": "Ghana",
      "home_odds": 1.6122,
      "draw_odds": 3.822,
      "away_odds": 5.6473,
      "p_home": 0.5857,
      "p_draw": 0.2471,
      "p_away": 0.1672,
      "bookmaker": "avg(41)",
      "source": "the-odds-api"
    },
    {
      "date": "2026-06-27",
      "home": "Egypt",
      "away": "Iran",
      "home_odds": 2.0781,
      "draw_odds": 3.1352,
      "away_odds": 3.8307,
      "p_home": 0.4535,
      "p_draw": 0.3006,
      "p_away": 0.246,
      "bookmaker": "avg(42)",
      "source": "the-odds-api"
    },
    {
      "date": "2026-06-27",
      "home": "New Zealand",
      "away": "Belgium",
      "home_odds": 12.1221,
      "draw_odds": 6.1593,
      "away_odds": 1.2226,
      "p_home": 0.0776,
      "p_draw": 0.1528,
      "p_away": 0.7696,
      "bookmaker": "avg(42)",
      "source": "the-odds-api"
    },
    {
      "date": "2026-06-27",
      "home": "Panama",
      "away": "England",
      "home_odds": 10.7151,
      "draw_odds": 6.299,
      "away_odds": 1.2402,
      "p_home": 0.0882,
      "p_draw": 0.15,
      "p_away": 0.7618,
      "bookmaker": "avg(41)",
      "source": "the-odds-api"
    },
    {
      "date": "2026-06-27",
      "home": "Uruguay",
      "away": "Spain",
      "home_odds": 5.9471,
      "draw_odds": 4.1507,
      "away_odds": 1.5388,
      "p_home": 0.1588,
      "p_draw": 0.2275,
      "p_away": 0.6137,
      "bookmaker": "avg(42)",
      "source": "the-odds-api"
    },
    {
      "date": "2026-06-28",
      "home": "Algeria",
      "away": "Austria",
      "home_odds": 3.0337,
      "draw_odds": 3.0434,
      "away_odds": 2.4629,
      "p_home": 0.3097,
      "p_draw": 0.3087,
      "p_away": 0.3815,
      "bookmaker": "avg(41)",
      "source": "the-odds-api"
    },
    {
      "date": "2026-06-28",
      "home": "Jordan",
      "away": "Argentina",
      "home_odds": 13.6924,
      "draw_odds": 6.7266,
      "away_odds": 1.1956,
      "p_home": 0.069,
      "p_draw": 0.1405,
      "p_away": 0.7905,
      "bookmaker": "avg(41)",
      "source": "the-odds-api"
    }
  ]
}
