{
  "updatedAt": "2026-07-07T03:29:31+00:00",
  "source": "the-odds-api",
  "sourcesTried": [
    {
      "source": "the-odds-api",
      "ok": true,
      "count": 5
    },
    {
      "source": "espn",
      "ok": false,
      "error": "'NoneType' object has no attribute 'get'"
    }
  ],
  "count": 5,
  "odds": [
    {
      "date": "2026-07-07",
      "home": "Argentina",
      "away": "Egypt",
      "home_odds": 1.3502,
      "draw_odds": 4.8438,
      "away_odds": 9.9636,
      "p_home": 0.7071,
      "p_draw": 0.1971,
      "p_away": 0.0958,
      "bookmaker": "avg(45)",
      "source": "the-odds-api"
    },
    {
      "date": "2026-07-07",
      "home": "Switzerland",
      "away": "Colombia",
      "home_odds": 3.5989,
      "draw_odds": 3.0902,
      "away_odds": 2.2353,
      "p_home": 0.2649,
      "p_draw": 0.3085,
      "p_away": 0.4265,
      "bookmaker": "avg(45)",
      "source": "the-odds-api"
    },
    {
      "date": "2026-07-09",
      "home": "France",
      "away": "Morocco",
      "home_odds": 1.5804,
      "draw_odds": 3.8882,
      "away_odds": 6.236,
      "p_home": 0.6024,
      "p_draw": 0.2449,
      "p_away": 0.1527,
      "bookmaker": "avg(45)",
      "source": "the-odds-api"
    },
    {
      "date": "2026-07-10",
      "home": "Spain",
      "away": "Belgium",
      "home_odds": 1.628,
      "draw_odds": 3.9432,
      "away_odds": 5.406,
      "p_home": 0.5834,
      "p_draw": 0.2409,
      "p_away": 0.1757,
      "bookmaker": "avg(40)",
      "source": "the-odds-api"
    },
    {
      "date": "2026-07-11",
      "home": "Norway",
      "away": "England",
      "home_odds": 4.0542,
      "draw_odds": 3.656,
      "away_odds": 1.8862,
      "p_home": 0.2348,
      "p_draw": 0.2604,
      "p_away": 0.5048,
      "bookmaker": "avg(45)",
      "source": "the-odds-api"
    }
  ]
}
