{
  "updatedAt": "2026-07-18T09:26:36+00:00",
  "source": "the-odds-api",
  "sourcesTried": [
    {
      "source": "the-odds-api",
      "ok": true,
      "count": 2
    },
    {
      "source": "espn",
      "ok": true,
      "count": 0
    }
  ],
  "count": 2,
  "odds": [
    {
      "date": "2026-07-18",
      "home": "France",
      "away": "England",
      "home_odds": 1.868,
      "draw_odds": 4.001,
      "away_odds": 3.81,
      "p_home": 0.5109,
      "p_draw": 0.2385,
      "p_away": 0.2505,
      "bookmaker": "avg(50)",
      "source": "the-odds-api"
    },
    {
      "date": "2026-07-19",
      "home": "Spain",
      "away": "Argentina",
      "home_odds": 2.2802,
      "draw_odds": 3.0276,
      "away_odds": 3.5926,
      "p_home": 0.4188,
      "p_draw": 0.3154,
      "p_away": 0.2658,
      "bookmaker": "avg(50)",
      "source": "the-odds-api"
    }
  ]
}
